synthetic_data_generator/__init__.py
synthetic_data_generator/src/__init__.py
synthetic_data_generator/src/data_generator.py
synthetic_data_generator/test/__init__.py
synthetic_data_generator/test/test_data_generator.py
auto_synth_data_gen-0.0.3.dist-info/LICENSE
auto_synth_data_gen-0.0.3.dist-info/METADATA
auto_synth_data_gen-0.0.3.dist-info/WHEEL
auto_synth_data_gen-0.0.3.dist-info/top_level.txt
auto_synth_data_gen-0.0.3.dist-info/RECORD
