Metadata-Version: 2.1
Name: auto-synth-data-gen
Version: 0.0.3
Summary: A Python package to generate synthetic datasets resembling real-world data
Home-page: https://github.com/Gouranga-GH/custom_pypi_sdg.git
Author: Gouranga Jha
Author-email: post.gourang@gmail.com
License: MIT
Classifier: License :: OSI Approved :: MIT License
Classifier: Programming Language :: Python :: 3
Classifier: Operating System :: OS Independent
Requires-Python: >=3.8
License-File: LICENSE
Requires-Dist: numpy >=1.24.4
Requires-Dist: pandas >=2.0.3
Provides-Extra: dev
Requires-Dist: pytest >=7.0 ; extra == 'dev'
Requires-Dist: twine >=5.1.1 ; extra == 'dev'
